progress_checkpoint/__init__.py
progress_checkpoint/asyn.py
progress_checkpoint/common.py
progress_checkpoint/console.py
progress_checkpoint/py.typed
progress_checkpoint/sync.py
progress_checkpoint-1.0.5.dist-info/LICENSE
progress_checkpoint-1.0.5.dist-info/METADATA
progress_checkpoint-1.0.5.dist-info/WHEEL
progress_checkpoint-1.0.5.dist-info/top_level.txt
progress_checkpoint-1.0.5.dist-info/RECORD
