Metadata-Version: 2.1
Name: progress-checkpoint
Version: 1.0.5
Summary: Helpers for reporting a progress from functions by the means of callbacks.
Home-page: https://github.com/peper0/progress-checkpoint
Author: Tomasz Lakota
Author-email: tomasz.lakota@gmail.com
License: MIT
Keywords: progress,progressbar,callback,reporting
Platform: UNKNOWN
Classifier: Development Status :: 5 - Production/Stable
Classifier: License :: OSI Approved :: MIT License
Classifier: Programming Language :: Python :: 3.10
Classifier: Programming Language :: Python :: 3.9
Classifier: Programming Language :: Python :: 3.8
Classifier: Programming Language :: Python :: 3.7
Classifier: Intended Audience :: Developers
Classifier: Operating System :: OS Independent
Classifier: Topic :: Software Development
Classifier: Topic :: Software Development :: Libraries :: Python Modules
Requires-Python: >=3.6
License-File: LICENSE
Requires-Dist: deprecation
Provides-Extra: progressbar
Requires-Dist: progressbar ; extra == 'progressbar'
